Metadata-Version: 2.1
Name: neon-solver-wolfram-alpha-plugin
Version: 0.0.2a0
Summary: A question solver plugin for ovos/neon/mycroft
Home-page: https://github.com/NeonGeckoCom/neon_solver_wolfram_alpha_plugin
Author: Neongecko
Author-email: developers@neon.ai
License: bsd3
Keywords: mycroft plugin utterance fallback query
Platform: UNKNOWN
Requires-Dist: neon-solvers (>=0.0.2a1,~=0.0)
Requires-Dist: requests
Requires-Dist: neon-lang-plugin-libretranslate
Requires-Dist: requests-cache
